concentration_lib/__init__.py
concentration_lib/concentration_bounds.py
concentration_lib/concentration_variance_bounds.py
concentration_lib/empirical_concentration_bounds.py
concentration_lib/empirical_uniform_concentration_bounds.py
concentration_lib/helper_ptlm.py
concentration_lib/uniform_bregman_concentration_bounds.py
concentration_lib/uniform_concentration_bounds.py
concentration_lib/utils.py
concentration_lib-0.2.0.dist-info/LICENSE
concentration_lib-0.2.0.dist-info/METADATA
concentration_lib-0.2.0.dist-info/WHEEL
concentration_lib-0.2.0.dist-info/top_level.txt
concentration_lib-0.2.0.dist-info/RECORD
