Metadata-Version: 2.1
Name: concentration-lib
Version: 0.2.0
Summary: Library for concentration bounds
Home-page: https://github.com/sauxpa/concentration_lib
Author: Patrick Saux
Author-email: patrick.saux@ginria.fr
Requires-Python: >=3.6
License-File: LICENSE
Requires-Dist: numpy
Requires-Dist: scipy
